bools/__init__.py
bools/datetime/__init__.py
bools/datetime/datetime.py
bools/datetime/timedelta.py
bools/dbc/__init__.py
bools/dbc/dbc.py
bools/dbc/elasticsearch.py
bools/dbc/influxdb.py
bools/functools/__init__.py
bools/functools/functools.py
bools/io/__init__.py
bools/io/file.py
bools/log/__init__.py
bools/log/logger.py
bools/mixin/__init__.py
bools/mixin/pandas.py
bools-0.5.0.data/data/README.md
bools-0.5.0.dist-info/LICENSE
bools-0.5.0.dist-info/METADATA
bools-0.5.0.dist-info/WHEEL
bools-0.5.0.dist-info/top_level.txt
bools-0.5.0.dist-info/RECORD
