Metadata-Version: 2.1
Name: bools
Version: 0.5.0
Summary: Collection of common tools in Python
Home-page: https://github.com/lotcher/bools
Author: bowaer
Author-email: me@lbj.wiki
License: MIT
Keywords: tools,datetime,logger,functools,elasticsearch,influxdb
Platform: UNKNOWN
Classifier: Programming Language :: Python :: 3.6
Requires-Dist: python-dateutil (>=2.8.1)
Requires-Dist: colorlog (>=5.0.1)
Requires-Dist: requests (>=2.0.1)
